ndlbulkdownload/__init__.py
ndlbulkdownload/_version.py
ndlbulkdownload/args.py
ndlbulkdownload/cli.py
ndlbulkdownload/version.py
ndlbulkdownload-0.2.0.dist-info/METADATA
ndlbulkdownload-0.2.0.dist-info/WHEEL
ndlbulkdownload-0.2.0.dist-info/entry_points.txt
ndlbulkdownload-0.2.0.dist-info/licenses/LICENSE.md
ndlbulkdownload-0.2.0.dist-info/RECORD
