Metadata-Version: 2.4
Name: ndlbulkdownload
Version: 0.2.0
Summary: Data Link CLI Bulk Download Utility
Project-URL: Homepage, https://github.com/nasdaq/ndlbulkdownload
Project-URL: Issues, https://github.com/nasdaq/ndlbulkdownload/issues
Project-URL: Changelog, https://github.com/nasdaq/ndlbulkdownload/blob/master/CHANGELOG.md
Maintainer-email: Nasdaq Data Link Development Team <connect@data.nasdaq.com>
License: MIT
License-File: LICENSE.md
Keywords: cli,console,data,datalink,economic,financial,nasdaq,nasdaq data link,terminal
Classifier: License :: OSI Approved :: MIT License
Classifier: Programming Language :: Python :: 3
Classifier: Programming Language :: Python :: 3 :: Only
Classifier: Programming Language :: Python :: 3.9
Classifier: Programming Language :: Python :: 3.10
Classifier: Programming Language :: Python :: 3.11
Classifier: Topic :: Terminals
Classifier: Topic :: Utilities
Requires-Python: >=3.9
Requires-Dist: requests
Requires-Dist: tqdm
Provides-Extra: build
Requires-Dist: build; extra == 'build'
Requires-Dist: twine; extra == 'build'
Provides-Extra: lint
Requires-Dist: pre-commit; extra == 'lint'
Requires-Dist: ruff; extra == 'lint'
